add_psd_layer/__init__.py
add_psd_layer/add_image_as_layer.py
add_psd_layer-0.1.0.dist-info/METADATA
add_psd_layer-0.1.0.dist-info/WHEEL
add_psd_layer-0.1.0.dist-info/entry_points.txt
add_psd_layer-0.1.0.dist-info/RECORD
