Metadata-Version: 2.3
Name: add_psd_layer
Version: 0.1.0
Summary: A CLI tool to add an image as a new layer to a PSD file
Project-URL: Homepage, https://github.com/ilya-kudravets/add_image_as_layer_to_psd
Project-URL: Bug Tracker, https://github.com/ilya-kudravets/add_image_as_layer_to_psd/issues
Author-email: Ilya Kudravets <ilya.kudravets@gmail.com>
Classifier: License :: OSI Approved :: MIT License
Classifier: Operating System :: OS Independent
Classifier: Programming Language :: Python :: 3
Requires-Python: >=3.11
Requires-Dist: cairosvg
Requires-Dist: pillow
Requires-Dist: psd-tools
